{"textures":{"0":"modelengine:entity/assaultron"},"elements":[{"from":[6.6610856,8.927673,6.9110856],"to":[8.161085,9.927673,8.411085],"faces":{"east":{"uv":[10.5,11.5,10.75,11.625],"tintindex":0,"rotation":0,"texture":"#0"},"south":{"uv":[11.5,10.625,11.75,10.75],"tintindex":0,"rotation":0,"texture":"#0"},"north":{"uv":[11.5,10.125,11.75,10.25],"tintindex":0,"rotation":0,"texture":"#0"},"west":{"uv":[11.5,10.75,11.75,10.875],"tintindex":0,"rotation":0,"texture":"#0"},"up":{"uv":[11.375,11.25,11.125,11.0],"tintindex":0,"rotation":0,"texture":"#0"},"down":{"uv":[11.5,0.0,11.25,0.25],"tintindex":0,"rotation":0,"texture":"#0"}},"rotation":{"origin":[7.4110856,9.427673,7.6610856],"angle":45.0,"axis":"y"}}],"display":{"gui":{"rotation":[30,225,0]}}}